turbolucene
