Metadata-Version: 1.0
Name: TurboLucene
Version: 0.2.2
Summary: TurboLucene is a TurboGears extension that allows applications to easily use the PyLucene full-text search engine.
Home-page: http://dev.krys.ca/turbolucene
Author: Krys Wilken
Author-email: krys AT krys DOT ca
License: MIT
Download-URL: http://dev.krys.ca/downloads/turbolucene
Keywords: turbolucene turbogears pylucene full text search engine turbogears.extension
Platform: UNKNOWN
Classifier: Development Status :: 3 - Alpha
Classifier: Environment :: Web Environment
Classifier: Framework :: TurboGears
Classifier: Intended Audience :: Developers
Classifier: License :: OSI Approved :: MIT License
Classifier: Operating System :: OS Independent
Classifier: Programming Language :: Python
Classifier: Topic :: Internet :: WWW/HTTP :: Indexing/Search
Classifier: Topic :: Software Development :: Libraries :: Python Modules
Classifier: Natural Language :: Czech
Classifier: Natural Language :: Danish
Classifier: Natural Language :: German
Classifier: Natural Language :: Greek
Classifier: Natural Language :: English
Classifier: Natural Language :: Spanish
Classifier: Natural Language :: Finnish
Classifier: Natural Language :: French
Classifier: Natural Language :: Italian
Classifier: Natural Language :: Japanese
Classifier: Natural Language :: Korean
Classifier: Natural Language :: Dutch
Classifier: Natural Language :: Norwegian
Classifier: Natural Language :: Portuguese
Classifier: Natural Language :: Portuguese (Brazilian)
Classifier: Natural Language :: Russian
Classifier: Natural Language :: Swedish
Classifier: Natural Language :: Chinese (Simplified)
